languageprocessing/__init__.py
languageprocessing/__main__.py
languageprocessing/example_scripy.py
languageprocessing/messaging.py
languageprocessing/parser.py
languageprocessing/partofspeech.py
languageprocessing/sentimentanalysis.py
languageprocessing-0.0.1.dist-info/DESCRIPTION.rst
languageprocessing-0.0.1.dist-info/METADATA
languageprocessing-0.0.1.dist-info/RECORD
languageprocessing-0.0.1.dist-info/WHEEL
languageprocessing-0.0.1.dist-info/metadata.json
languageprocessing-0.0.1.dist-info/top_level.txt
