Metadata-Version: 2.0
Name: languageprocessing
Version: 0.0.1
Summary: Simple language processing with zeromq
Home-page: https://github.com/benhoff/languageprocessing
Author: Ben Hoff
Author-email: beohoff@gmail.com
License: GPL3
Platform: UNKNOWN
Classifier: Development Status :: 1 - Planning
Classifier: Intended Audience :: Developers
Classifier: License :: OSI Approved :: GNU General Public License v3 (GPLv3)
Classifier: Programming Language :: Python :: 3
Classifier: Programming Language :: Python :: 3.5
Classifier: Topic :: Utilities
Classifier: Operating System :: OS Independent
Requires-Dist: pyzmq
Requires-Dist: textblob
Provides-Extra: dev
Requires-Dist: flake8; extra == 'dev'
